bramble/__init__.py
bramble/contextual.py
bramble/loggers.py
bramble/logs.py
bramble/stdlib.py
bramble/utils.py
bramble/wrapper.py
bramble/backends/__init__.py
bramble/backends/base.py
bramble/backends/file_backend.py
bramble/backends/redis_backend.py
bramble/ui/__init__.py
bramble/ui/bramble_ui.py
bramble/ui/copy_button.py
bramble/ui/data.py
bramble/ui/datetime_input.py
bramble/ui/logs.py
bramble/ui/main.py
bramble/ui/navigation.py
bramble/ui/search.py
bramble/ui/styles.css
bramble/ui/styles.py
bramble-1.2.0.dist-info/METADATA
bramble-1.2.0.dist-info/WHEEL
bramble-1.2.0.dist-info/entry_points.txt
bramble-1.2.0.dist-info/licenses/LICENSE
bramble-1.2.0.dist-info/RECORD
