Metadata-Version: 2.4
Name: bramble
Version: 1.2.0
Summary: Tree based logging for async python
Project-URL: Homepage, https://github.com/HesitantlyHuman/bramble
Project-URL: Repository, https://github.com/HesitantlyHuman/bramble
Author-email: Tanner Sims <tannersims@hesitantlyhuman.com>
License-File: LICENSE
Keywords: async,bramble,branch,log,logging,python,scoped,threading,tree,ui
Requires-Python: >=3.11
Provides-Extra: dev
Requires-Dist: black; extra == 'dev'
Requires-Dist: pytest; extra == 'dev'
Provides-Extra: redis
Requires-Dist: msgpack; extra == 'redis'
Requires-Dist: redis>=4.2.0rc1; extra == 'redis'
Provides-Extra: ui
Requires-Dist: streamlit; extra == 'ui'
